{
	"name": "sink_dataset",
	"properties": {
		"linkedServiceName": {
			"referenceName": "target_AzureDataLakeStorage1",
			"type": "LinkedServiceReference"
		},
		"annotations": [],
		"type": "DelimitedText",
		"typeProperties": {
			"location": {
				"type": "AzureBlobFSLocation",
				"fileName": "cleaned_dimcustomer.parquet",
				"folderPath": "silver",
				"fileSystem": "staging"
			},
			"columnDelimiter": ",",
			"escapeChar": "\\",
			"firstRowAsHeader": true,
			"quoteChar": "\""
		},
		"schema": []
	},
	"type": "Microsoft.DataFactory/factories/datasets"
}